model_mp_core/__init__.py
model_mp_core/base.py
model_mp_core/classification.py
model_mp_core/detection.py
model_mp_core/preprocess.py
model_mp_core/segmentation.py
model_mp_core/tinyml.py
model_mp_core-0.1.6.dist-info/LICENSE
model_mp_core-0.1.6.dist-info/METADATA
model_mp_core-0.1.6.dist-info/WHEEL
model_mp_core-0.1.6.dist-info/top_level.txt
model_mp_core-0.1.6.dist-info/RECORD
