Metadata-Version: 2.1
Name: model-mp-core
Version: 0.1.6
Summary: Core inference library for Mind+ model training tool
Home-page: https://github.com/UNIHIKER/model-pypi-lib
Author: unihiker Team
Author-email: unihiker Team <unihiker@dfrobot.com>
License: MIT License
Project-URL: Homepage, https://github.com/UNIHIKER/model-pypi-lib
Project-URL: Bug Tracker, https://github.com/UNIHIKER/model-pypi-lib/issues
Classifier: Programming Language :: Python :: 3
Classifier: License :: OSI Approved :: MIT License
Classifier: Operating System :: OS Independent
Classifier: Intended Audience :: Education
Classifier: Intended Audience :: Developers
Classifier: Topic :: Software Development :: Libraries :: Python Modules
Classifier: Topic :: Scientific/Engineering :: Artificial Intelligence
Classifier: Topic :: Education
Requires-Python: >=3.7
License-File: LICENSE
Requires-Dist: numpy>=1.19.0
Requires-Dist: opencv-python>=4.5.0
Requires-Dist: pillow>=8.0.0
Requires-Dist: onnxruntime>=1.8.0
Requires-Dist: pyyaml>=5.1.0
Requires-Dist: scikit-learn>=1.7.1
Requires-Dist: pydantic>=2.12.3
Requires-Dist: scipy>=1.16.2
